acronym/__init__.py
acronym/acronym.py
acronym/alias_utils.py
acronym/help_text.py
acronym/data/aliases.sh
acronym/data/aliases.toml
acronym/data/keywords.toml
acronym_alias-0.1.0.data/data/share/bash-completion/completions/_acronym
acronym_alias-0.1.0.data/data/share/man/acronym.1.md
acronym_alias-0.1.0.data/data/share/man/man1/acronym.1
acronym_alias-0.1.0.data/data/share/zsh/site-functions/_acronym
acronym_alias-0.1.0.dist-info/entry_points.txt
acronym_alias-0.1.0.dist-info/LICENSE
acronym_alias-0.1.0.dist-info/WHEEL
acronym_alias-0.1.0.dist-info/METADATA
acronym_alias-0.1.0.dist-info/RECORD
