Metadata-Version: 2.1
Name: acronym-alias
Version: 0.1.0
Summary: A smart alias management system to shorten your shell commands.
Keywords: alias,shell,productivity,development
Author-email: Chinar Joshi <chinarjoshi7@gmail.com>
Requires-Python: >=3.10
Classifier: Programming Language :: Python :: 3
Classifier: License :: OSI Approved :: MIT License
Classifier: Operating System :: OS Independent
Requires-Dist: toml
Project-URL: Bug Tracker, https://github.com/chinarjoshi/acronym/issues
Project-URL: Homepage, https://github.com/chinarjoshi/acronym
